location_api/__init__.py
location_api/admin.py
location_api/apps.py
location_api/models.py
location_api/serializers.py
location_api/views.py
location_api/migrations/0001_initial.py
location_api/migrations/0002_location_archived.py
location_api/migrations/__init__.py
location_api/urls/__init__.py
location_api/urls/base.py
location_api/urls/search.py
django_location_api-0.1.1.dist-info/METADATA
django_location_api-0.1.1.dist-info/WHEEL
django_location_api-0.1.1.dist-info/licenses/AUTHORS.rst
django_location_api-0.1.1.dist-info/licenses/LICENSE
django_location_api-0.1.1.dist-info/RECORD
