Metadata-Version: 2.4
Name: django-location-api
Version: 0.1.1
Summary: Django package for location services
Project-URL: Homepage, https://github.com/carlosfunk/django-location-api
Author-email: Carl Robben <carl@successmonkey.co.nz>
License-Expression: BSD-3-Clause
License-File: AUTHORS.rst
License-File: LICENSE
Classifier: Development Status :: 2 - Pre-Alpha
Classifier: Environment :: Web Environment
Classifier: Framework :: Django
Classifier: Framework :: Django :: 4.1
Classifier: Intended Audience :: Developers
Classifier: License :: OSI Approved :: BSD License
Classifier: Natural Language :: English
Classifier: Programming Language :: Python :: 3
Classifier: Programming Language :: Python :: 3 :: Only
Classifier: Programming Language :: Python :: 3.10
Classifier: Programming Language :: Python :: 3.11
Classifier: Programming Language :: Python :: 3.12
Classifier: Topic :: Internet :: WWW/HTTP
Classifier: Topic :: Internet :: WWW/HTTP :: Dynamic Content
Requires-Python: <4,>=3.10
Requires-Dist: django-filter~=24.3
Requires-Dist: djangorestframework-gis~=1.0
Requires-Dist: djangorestframework<4,>=3.14.0
Requires-Dist: django~=4.2
